grabber/__init__.py
grabber/_dock_widget.py
grabber/_version.py
grabber/anchors.py
grabber/grabber.py
grabber/grabberwidget.py
grabber/_tests/__init__.py
grabber/_tests/test_dock_widget.py
grabber_ift-0.2.2.dist-info/LICENSE
grabber_ift-0.2.2.dist-info/METADATA
grabber_ift-0.2.2.dist-info/WHEEL
grabber_ift-0.2.2.dist-info/entry_points.txt
grabber_ift-0.2.2.dist-info/top_level.txt
grabber_ift-0.2.2.dist-info/RECORD
