Metadata-Version: 2.1
Name: grabber-ift
Version: 0.2.2
Summary: A tool for contour-based segmentation correction (2D only).
Home-page: UNKNOWN
Author: Jordão Bragantini
Author-email: jordao.bragantini@gmail.com
License: MIT
Platform: UNKNOWN
Classifier: Development Status :: 2 - Pre-Alpha
Classifier: Intended Audience :: Developers
Classifier: Framework :: napari
Classifier: Topic :: Software Development :: Testing
Classifier: Programming Language :: Python
Classifier: Programming Language :: Python :: 3
Classifier: Programming Language :: Python :: 3.7
Classifier: Programming Language :: Python :: 3.8
Classifier: Programming Language :: Python :: 3.9
Classifier: Operating System :: OS Independent
Classifier: License :: OSI Approved :: MIT License
Requires-Python: >=3.7
License-File: LICENSE
Requires-Dist: napari-plugin-engine (>=0.1.4)
Requires-Dist: pyift (>=0.0.4)
Requires-Dist: opencv-python-headless (>=4.4.0)
Requires-Dist: scipy (>=1.7.2)
